pesq_core.cpython-37m-x86_64-linux-gnu.so
pypesq/__init__.py
pypesq/comp.py
pypesq/main.py
pypesq/metrics.py
pypesq/parse.py
pypesq/save.py
pypesq/utils.py
objective_speech_metric-0.0.1.dist-info/LICENSE
objective_speech_metric-0.0.1.dist-info/METADATA
objective_speech_metric-0.0.1.dist-info/WHEEL
objective_speech_metric-0.0.1.dist-info/top_level.txt
objective_speech_metric-0.0.1.dist-info/RECORD
