Metadata-Version: 2.1
Name: objective-speech-metric
Version: 0.0.1
Summary: A package to compute pesq score.
Home-page: https://github.com/vBaiCai/python-pesq
License: MIT
Platform: UNKNOWN
Requires-Python: !=3.0.*, !=3.1.*, !=3.2.*, <4
Requires-Dist: numpy
